devpi_lockdown/__init__.py
devpi_lockdown/main.py
devpi_lockdown/templates/login.pt
devpi_lockdown/templates/logout.pt
devpi_lockdown-2.0.0.dist-info/METADATA
devpi_lockdown-2.0.0.dist-info/WHEEL
devpi_lockdown-2.0.0.dist-info/entry_points.txt
devpi_lockdown-2.0.0.dist-info/top_level.txt
devpi_lockdown-2.0.0.dist-info/RECORD
