Metadata-Version: 2.1
Name: devpi-lockdown
Version: 2.0.0
Summary: devpi-lockdown: tools to enable authentication for read access
Home-page: https://github.com/devpi/devpi-lockdown
Maintainer: Florian Schulze
Maintainer-email: mail@florian-schulze.net
License: MIT
Platform: UNKNOWN
Classifier: Environment :: Web Environment
Classifier: Intended Audience :: Developers
Classifier: Intended Audience :: System Administrators
Classifier: License :: OSI Approved :: MIT License
Classifier: Programming Language :: Python
Classifier: Programming Language :: Python :: 3
Classifier: Programming Language :: Python :: 3.6
Classifier: Programming Language :: Python :: 3.7
Classifier: Programming Language :: Python :: 3.8
Classifier: Programming Language :: Python :: 3.9
Requires-Python: >=3.6
Requires-Dist: devpi-web
Provides-Extra: tests
Requires-Dist: webtest ; extra == 'tests'
Requires-Dist: mock ; extra == 'tests'
Requires-Dist: devpi-client ; extra == 'tests'
Requires-Dist: pytest ; extra == 'tests'
Requires-Dist: pytest-cov ; extra == 'tests'
Requires-Dist: pytest-flake8 ; extra == 'tests'
